epg_grabber/__init__.py
epg_grabber/base.py
epg_grabber/cli.py
epg_grabber/exceptions.py
epg_grabber/generator.py
epg_grabber/sources/__init__.py
epg_grabber/sources/blesk_cz.py
epg_grabber/sources/centrum_cz.py
epg_grabber-2.1.0.dist-info/licenses/LICENSE
tests/__init__.py
tests/test_base.py
tests/test_blesk_cz.py
tests/test_centrum_cz.py
tests/test_cli.py
tests/test_config_loading.py
tests/test_exceptions.py
tests/test_generator.py
tests/test_sources.py
epg_grabber-2.1.0.dist-info/METADATA
epg_grabber-2.1.0.dist-info/WHEEL
epg_grabber-2.1.0.dist-info/entry_points.txt
epg_grabber-2.1.0.dist-info/top_level.txt
epg_grabber-2.1.0.dist-info/RECORD
